src/__init__.py
src/main.py
python_project_template_poetry-0.1.0.dev8.dist-info/LICENSE.md
python_project_template_poetry-0.1.0.dev8.dist-info/METADATA
python_project_template_poetry-0.1.0.dev8.dist-info/WHEEL
python_project_template_poetry-0.1.0.dev8.dist-info/RECORD
