Metadata-Version: 2.1
Name: python-project-template-poetry
Version: 0.1.0.dev8
Summary: A project template to use for new Python Github repositories with best practices.
Home-page: https://github.com/azataiot/python-project-template
License: MIT
Author: Azat
Author-email: 8280770+azataiot@users.noreply.github.com
Requires-Python: >=3.9,<4.0
Classifier: License :: OSI Approved :: MIT License
Classifier: Programming Language :: Python :: 3
Classifier: Programming Language :: Python :: 3.9
Classifier: Programming Language :: Python :: 3.10
Classifier: Programming Language :: Python :: 3.11
